igwn_segments/__init__.py
igwn_segments/__segments.cpython-313-x86_64-linux-musl.so
igwn_segments/_version.py
igwn_segments/utils.py
igwn_segments-2.0.0.dist-info/LICENSE
igwn_segments-2.0.0.dist-info/METADATA
igwn_segments-2.0.0.dist-info/WHEEL
igwn_segments-2.0.0.dist-info/top_level.txt
igwn_segments-2.0.0.dist-info/RECORD
