Metadata-Version: 2.1
Name: igwn-segments
Version: 2.0.0
Summary: Representations of semi-open intervals
Author-email: Kipp Cannon <kipp.cannon@ligo.org>, Tito Dal Canton <tito.canton@ligo.org>, Duncan Macleod <duncan.macleod@ligo.org>, Leo Singer <leo.singer@ligo.org>
License: GPL-3.0-or-later
Classifier: Development Status :: 5 - Production/Stable
Classifier: Programming Language :: Python
Classifier: Programming Language :: Python :: 3.6
Classifier: Programming Language :: Python :: 3.9
Classifier: Programming Language :: Python :: 3.10
Classifier: Programming Language :: Python :: 3.11
Classifier: Programming Language :: Python :: 3.12
Classifier: Programming Language :: Python :: 3.13
Classifier: Intended Audience :: Science/Research
Classifier: Intended Audience :: End Users/Desktop
Classifier: Intended Audience :: Developers
Classifier: Natural Language :: English
Classifier: Topic :: Scientific/Engineering
Classifier: Topic :: Scientific/Engineering :: Astronomy
Classifier: Topic :: Scientific/Engineering :: Physics
Classifier: Operating System :: POSIX
Classifier: Operating System :: Unix
Classifier: Operating System :: MacOS
Classifier: License :: OSI Approved :: GNU General Public License v3 (GPLv3)
License-File: LICENSE
Provides-Extra: docs
Requires-Dist: furo; extra == "docs"
Requires-Dist: Sphinx; extra == "docs"
Requires-Dist: sphinx-automodapi; extra == "docs"
Requires-Dist: sphinx-design; extra == "docs"
